FinPay/__init__.py
FinPay-0.1.0.dist-info/LICENSE.txt
FinPay-0.1.0.dist-info/METADATA
FinPay-0.1.0.dist-info/WHEEL
FinPay-0.1.0.dist-info/top_level.txt
FinPay-0.1.0.dist-info/RECORD
