Metadata-Version: 2.1
Name: FinPay
Version: 0.1.0
Summary: A module to work with api API
Home-page: https://github.com/WallD3v/FinPay
Author: WallDev
Author-email: walldevnewthon@gmail.com
License: MIT
License-File: LICENSE.txt
